yafowil.widget.autocomplete-1.8-py3.9-nspkg.pth
yafowil/widget/autocomplete/__init__.py
yafowil/widget/autocomplete/example.py
yafowil/widget/autocomplete/tests.py
yafowil/widget/autocomplete/widget.py
yafowil/widget/autocomplete/resources/jquery.ui.autocomplete.bootstrap.css
yafowil/widget/autocomplete/resources/jquery.ui.autocomplete.css
yafowil/widget/autocomplete/resources/jquery.ui.autocomplete.js
yafowil/widget/autocomplete/resources/jquery.ui.autocomplete.min.js
yafowil/widget/autocomplete/resources/jquery.ui.autocomplete.plone5.css
yafowil/widget/autocomplete/resources/jquery.ui.menu.bootstrap.css
yafowil/widget/autocomplete/resources/jquery.ui.menu.css
yafowil/widget/autocomplete/resources/jquery.ui.menu.js
yafowil/widget/autocomplete/resources/jquery.ui.menu.min.js
yafowil/widget/autocomplete/resources/jquery.ui.menu.plone5.css
yafowil/widget/autocomplete/resources/widget.css
yafowil/widget/autocomplete/resources/widget.js
yafowil_widget_autocomplete-1.8.dist-info/licenses/LICENSE.rst
yafowil_widget_autocomplete-1.8.dist-info/METADATA
yafowil_widget_autocomplete-1.8.dist-info/WHEEL
yafowil_widget_autocomplete-1.8.dist-info/entry_points.txt
yafowil_widget_autocomplete-1.8.dist-info/namespace_packages.txt
yafowil_widget_autocomplete-1.8.dist-info/top_level.txt
yafowil_widget_autocomplete-1.8.dist-info/RECORD
